{
  "features": [
    {
      "type": "Feature",
      "properties": {
         "zoneId": 6
      },
      "geometry": {
        "coordinates": [
          [
            [
              -56.186362,
              -34.909235
            ],
            [
              -56.185971,
              -34.912035
            ],
            [
              -56.183482,
              -34.912705
            ],
            [
              -56.181313,
              -34.91393
            ],
            [
              -56.178581,
              -34.914468
            ],
            [
              -56.179464,
              -34.908769
            ],
            [
              -56.186362,
              -34.909235
            ]
          ]
        ],
        "type": "Polygon"
      },
      "id": "00897a68418c8d91ec774fe129e7c448"
    }]}